LICENSE
MANIFEST.in
README.rst
setup.py
django_lbattachment.egg-info/PKG-INFO
django_lbattachment.egg-info/SOURCES.txt
django_lbattachment.egg-info/dependency_links.txt
django_lbattachment.egg-info/not-zip-safe
django_lbattachment.egg-info/requires.txt
django_lbattachment.egg-info/top_level.txt
lbattachment/__init__.py
lbattachment/admin.py
lbattachment/forms.py
lbattachment/models.py
lbattachment/settings.py
lbattachment/urls.py
lbattachment/views.py
lbattachment/tests/__init__.py
lbattachment/tests/tests.py
lbattachment/tests/urls.py